fast_rich-0.3.1.dist-info/METADATA
fast_rich-0.3.1.dist-info/WHEEL
fast_rich/README.md
fast_rich/__init__.py
fast_rich/__pycache__/__init__.cpython-314.pyc
fast_rich/__pycache__/_print.cpython-314.pyc
fast_rich/__pycache__/abc.cpython-314.pyc
fast_rich/__pycache__/align.cpython-314.pyc
fast_rich/__pycache__/ansi.cpython-314.pyc
fast_rich/__pycache__/bar.cpython-314.pyc
fast_rich/__pycache__/box.cpython-314.pyc
fast_rich/__pycache__/cells.cpython-314.pyc
fast_rich/__pycache__/color.cpython-314.pyc
fast_rich/__pycache__/color_triplet.cpython-314.pyc
fast_rich/__pycache__/columns.cpython-314.pyc
fast_rich/__pycache__/console.cpython-314.pyc
fast_rich/__pycache__/console_options.cpython-314.pyc
fast_rich/__pycache__/constrain.cpython-314.pyc
fast_rich/__pycache__/containers.cpython-314.pyc
fast_rich/__pycache__/control.cpython-314.pyc
fast_rich/__pycache__/default_styles.cpython-314.pyc
fast_rich/__pycache__/diagnose.cpython-314.pyc
fast_rich/__pycache__/emoji.cpython-314.pyc
fast_rich/__pycache__/errors.cpython-314.pyc
fast_rich/__pycache__/file_proxy.cpython-314.pyc
fast_rich/__pycache__/filesize.cpython-314.pyc
fast_rich/__pycache__/highlighter.cpython-314.pyc
fast_rich/__pycache__/inspect.cpython-314.pyc
fast_rich/__pycache__/json.cpython-314.pyc
fast_rich/__pycache__/jupyter.cpython-314.pyc
fast_rich/__pycache__/layout.cpython-314.pyc
fast_rich/__pycache__/live.cpython-314.pyc
fast_rich/__pycache__/live_render.cpython-314.pyc
fast_rich/__pycache__/logging.cpython-314.pyc
fast_rich/__pycache__/markdown.cpython-314.pyc
fast_rich/__pycache__/markup.cpython-314.pyc
fast_rich/__pycache__/measure.cpython-314.pyc
fast_rich/__pycache__/padding.cpython-314.pyc
fast_rich/__pycache__/pager.cpython-314.pyc
fast_rich/__pycache__/palette.cpython-314.pyc
fast_rich/__pycache__/panel.cpython-314.pyc
fast_rich/__pycache__/pretty.cpython-314.pyc
fast_rich/__pycache__/progress.cpython-314.pyc
fast_rich/__pycache__/progress_bar.cpython-314.pyc
fast_rich/__pycache__/prompt.cpython-314.pyc
fast_rich/__pycache__/protocol.cpython-314.pyc
fast_rich-0.3.1.dist-info/RECORD
