Metadata-Version: 2.4
Name: fast-rich
Version: 0.3.1
Classifier: Development Status :: 4 - Beta
Classifier: Environment :: Console
Classifier: Intended Audience :: Developers
Classifier: License :: OSI Approved :: MIT License
Classifier: Operating System :: OS Independent
Classifier: Programming Language :: Python :: 3
Classifier: Programming Language :: Python :: 3.10
Classifier: Programming Language :: Python :: 3.11
Classifier: Programming Language :: Python :: 3.12
Classifier: Programming Language :: Python :: 3.13
Classifier: Programming Language :: Python :: 3.14
Classifier: Programming Language :: Rust
Classifier: Topic :: Terminals
Classifier: Typing :: Typed
Requires-Dist: pytest>=7.0 ; extra == 'dev'
Requires-Dist: rich>=13.0 ; extra == 'dev'
Provides-Extra: dev
Summary: A drop-in replacement for Python Rich, powered by Rust for maximum performance
Keywords: terminal,console,rich,formatting,rust,fast
Author-email: Mohammad Albarham <mohammad.albarham@gmail.com>
License: MIT
Requires-Python: >=3.10
Project-URL: Homepage, https://github.com/mohammad-albarham/fast-rich
Project-URL: Repository, https://github.com/mohammad-albarham/fast-rich
Project-URL: Documentation, https://mohammad-albarham.github.io/fast-rich
